llmbrick/__init__.py
llmbrick/version.py
llmbrick/bricks/__init__.py
llmbrick/bricks/common/__init__.py
llmbrick/bricks/common/common.py
llmbrick/bricks/compose/__init__.py
llmbrick/bricks/compose/base_compose.py
llmbrick/bricks/guard/__init__.py
llmbrick/bricks/guard/base_guard.py
llmbrick/bricks/intention/__init__.py
llmbrick/bricks/intention/base_intention.py
llmbrick/bricks/llm/__init__.py
llmbrick/bricks/llm/base_llm.py
llmbrick/bricks/llm/openai_llm.py
llmbrick/bricks/rectify/__init__.py
llmbrick/bricks/rectify/base_rectify.py
llmbrick/bricks/retrieval/__init__.py
llmbrick/bricks/retrieval/base_retrieval.py
llmbrick/bricks/translate/__init__.py
llmbrick/bricks/translate/base_translate.py
llmbrick/core/__init__.py
llmbrick/core/brick.py
llmbrick/core/error_codes.py
llmbrick/core/exceptions.py
llmbrick/protocols/__init__.py
llmbrick/protocols/grpc/__init__.py
llmbrick/protocols/grpc/common/__init__.py
llmbrick/protocols/grpc/common/common.proto
llmbrick/protocols/grpc/common/common_pb2.py
llmbrick/protocols/grpc/common/common_pb2_grpc.py
llmbrick/protocols/grpc/compose/__init__.py
llmbrick/protocols/grpc/compose/compose.proto
llmbrick/protocols/grpc/compose/compose_pb2.py
llmbrick/protocols/grpc/compose/compose_pb2_grpc.py
llmbrick/protocols/grpc/guard/__init__.py
llmbrick/protocols/grpc/guard/guard.proto
llmbrick/protocols/grpc/guard/guard_pb2.py
llmbrick/protocols/grpc/guard/guard_pb2_grpc.py
llmbrick/protocols/grpc/intention/__init__.py
llmbrick/protocols/grpc/intention/intention.proto
llmbrick/protocols/grpc/intention/intention_pb2.py
llmbrick/protocols/grpc/intention/intention_pb2_grpc.py
llmbrick/protocols/grpc/llm/__init__.py
llmbrick/protocols/grpc/llm/llm.proto
llmbrick/protocols/grpc/llm/llm_pb2.py
llmbrick/protocols/grpc/llm/llm_pb2_grpc.py
llmbrick/protocols/grpc/rectify/__init__.py
llmbrick/protocols/grpc/rectify/rectify.proto
llmbrick/protocols/grpc/rectify/rectify_pb2.py
llmbrick/protocols/grpc/rectify/rectify_pb2_grpc.py
llmbrick-0.2.8.dist-info/licenses/LICENSE
llmbrick-0.2.8.dist-info/METADATA
llmbrick-0.2.8.dist-info/WHEEL
llmbrick-0.2.8.dist-info/entry_points.txt
llmbrick-0.2.8.dist-info/top_level.txt
llmbrick-0.2.8.dist-info/RECORD
