Metadata-Version: 2.4
Name: llmbrick
Version: 0.2.8
Summary: A modular LLM application development framework
Home-page: https://github.com/llmbrick/llmbrick
Author: LLMBrick Team
Author-email: LLMBrick Team <team@llmbrick.dev>
License: MIT
Project-URL: Homepage, https://github.com/JiHungLin/llmbrick
Project-URL: Documentation, https://jihunglin.github.io/llmbrick/
Project-URL: Repository, https://github.com/JiHungLin/llmbrick
Project-URL: Issues, https://github.com/JiHungLin/llmbrick/issues
Classifier: Development Status :: 3 - Alpha
Classifier: Intended Audience :: Developers
Classifier: License :: OSI Approved :: MIT License
Classifier: Operating System :: OS Independent
Classifier: Programming Language :: Python :: 3
Classifier: Programming Language :: Python :: 3.9
Classifier: Programming Language :: Python :: 3.10
Classifier: Programming Language :: Python :: 3.11
Classifier: Topic :: Software Development :: Libraries :: Python Modules
Classifier: Topic :: Scientific/Engineering :: Artificial Intelligence
Requires-Python: >=3.8
License-File: LICENSE
Requires-Dist: fastapi>=0.104.0
Requires-Dist: uvicorn[standard]>=0.24.0
Requires-Dist: pydantic>=2.5.0
Requires-Dist: pyyaml>=6.0.1
Requires-Dist: aiofiles>=23.2.1
Requires-Dist: openai>=1.3.0
Requires-Dist: websockets>=12.0
Requires-Dist: grpcio>=1.59.0
Requires-Dist: grpcio-tools>=1.59.0
Requires-Dist: sse-starlette>=1.6.5
Requires-Dist: chromadb>=0.4.15
Requires-Dist: httpx>=0.25.0
Requires-Dist: python-multipart>=0.0.6
Requires-Dist: pretty-loguru>=1.1.2
Requires-Dist: deprecated>=1.2.14
Requires-Dist: psutil>=5.9.0
Provides-Extra: dev
Requires-Dist: pytest>=7.4.0; extra == "dev"
Requires-Dist: pytest-asyncio>=0.21.0; extra == "dev"
Requires-Dist: pytest-cov>=4.1.0; extra == "dev"
Requires-Dist: pytest-mock>=3.11.0; extra == "dev"
Requires-Dist: black>=23.9.0; extra == "dev"
Requires-Dist: isort>=5.12.0; extra == "dev"
Requires-Dist: flake8>=6.1.0; extra == "dev"
Requires-Dist: mypy>=1.6.0; extra == "dev"
Requires-Dist: mkdocs>=1.5.0; extra == "dev"
Requires-Dist: mkdocs-material>=9.4.0; extra == "dev"
Requires-Dist: pre-commit>=3.5.0; extra == "dev"
Requires-Dist: twine>=4.0.0; extra == "dev"
Requires-Dist: build>=1.0.0; extra == "dev"
Dynamic: author
Dynamic: home-page
Dynamic: license-file
Dynamic: requires-python
